mcp_kinetica/__init__.py
mcp_kinetica/server_ki.py
mcp_kinetica/server_li.py
mcp_kinetica/features/__init__.py
mcp_kinetica/features/generate_sql.py
mcp_kinetica/features/kinetica_sql_system_prompt.md
mcp_kinetica/features/sql_context.py
mcp_kinetica/features/sql_tools.py
mcp_kinetica/features/table_monitor.py
mcp_kinetica/features/table_tools.py
mcp_kinetica/features/util.py
mcp_kinetica-7.2.3.1.dist-info/licenses/LICENSE
mcp_kinetica-7.2.3.1.dist-info/METADATA
mcp_kinetica-7.2.3.1.dist-info/WHEEL
mcp_kinetica-7.2.3.1.dist-info/entry_points.txt
mcp_kinetica-7.2.3.1.dist-info/top_level.txt
mcp_kinetica-7.2.3.1.dist-info/RECORD
