Metadata-Version: 2.4
Name: mcp-kinetica
Version: 7.2.3.1
Summary: MCP Server for Kinetica Database
License-Expression: MIT
Project-URL: Homepage, https://github.com/kineticadb/mcp-kinetica/
Keywords: kinetica,gpudb
Classifier: Programming Language :: Python :: 3
Classifier: Topic :: Database
Requires-Python: >=3.10
License-File: LICENSE
Requires-Dist: fastmcp>=2.7.1
Requires-Dist: gpudb>=7.2.2.9
Dynamic: license-file
